greatfet/__init__.py
greatfet/board.py
greatfet/errors.py
greatfet/greatfet.py
greatfet/interface.py
greatfet/neighbor.py
greatfet/peripherals.py
greatfet/programmer.py
greatfet/sensor.py
greatfet/utils.py
greatfet/assets/54-greatfet-plugdev.rules
greatfet/assets/54-greatfet-uaccess.rules
greatfet/assets/LPC43xx_43Sxx.svd
greatfet/assets/README
greatfet/assets/flash_stub.bin
greatfet/assets/greatfet_usb.bin
greatfet/boards/__init__.py
greatfet/boards/flash_stub.py
greatfet/boards/legacy.py
greatfet/boards/one.py
greatfet/boards/rad1o.py
greatfet/boards/xplorer.py
greatfet/commands/__init__.py
greatfet/commands/gf.py
greatfet/commands/greatfet_DS18B20.py
greatfet/commands/greatfet_adc.py
greatfet/commands/greatfet_adf7242.py
greatfet/commands/greatfet_chipcon.py
greatfet/commands/greatfet_dac.py
greatfet/commands/greatfet_dmesg.py
greatfet/commands/greatfet_firmware.py
greatfet/commands/greatfet_host_tools.py
greatfet/commands/greatfet_i2c.py
greatfet/commands/greatfet_info.py
greatfet/commands/greatfet_jtag.py
greatfet/commands/greatfet_led.py
greatfet/commands/greatfet_loadable.py
greatfet/commands/greatfet_logic.py
greatfet/commands/greatfet_msp430.py
greatfet/commands/greatfet_pattern.py
greatfet/commands/greatfet_pirate.py
greatfet/commands/greatfet_sdir.py
greatfet/commands/greatfet_selftest.py
greatfet/commands/greatfet_shell.py
greatfet/commands/greatfet_spi.py
greatfet/commands/greatfet_spiflash.py
greatfet/commands/greatfet_test.py
greatfet/commands/greatfet_uart.py
greatfet/commands/greatfet_usb_capture.py
greatfet/debug/__init__.py
greatfet/debug/lpc43xx.py
greatfet/debug/svd.py
greatfet/examples/gpio_pin_modes.py
greatfet/examples/greatfet_flame
greatfet/glitchkit/__init__.py
greatfet/glitchkit/base.py
greatfet/glitchkit/simple.py
greatfet/glitchkit/uart.py
greatfet/glitchkit/usb.py
greatfet/gnuradio/__init__.py
greatfet/gnuradio/adc.block.yml
greatfet/gnuradio/adc.py
greatfet/gnuradio/block.py
greatfet/gnuradio/gladiolus.py
greatfet-2025.0.0.dist-info/METADATA
greatfet-2025.0.0.dist-info/WHEEL
greatfet-2025.0.0.dist-info/entry_points.txt
greatfet-2025.0.0.dist-info/top_level.txt
greatfet-2025.0.0.dist-info/RECORD
