Metadata-Version: 2.4
Name: greatfet
Version: 2025.0.0
Summary: Python library for hardware hacking with the GreatFET
Author-email: Great Scott Gadgets <dev@greatscottgadgets.com>
License: BSD
Project-URL: Documentation, https://greatfet.readthedocs.io
Project-URL: Repository, https://github.com/greatscottgadgets/greatfet
Project-URL: Issues, https://github.com/greatscottgadgets/greatfet/issues
Classifier: Programming Language :: Python
Classifier: Development Status :: 5 - Production/Stable
Classifier: Natural Language :: English
Classifier: Environment :: Console
Classifier: Environment :: Plugins
Classifier: Intended Audience :: Developers
Classifier: Intended Audience :: Science/Research
Classifier: License :: OSI Approved :: BSD License
Classifier: Operating System :: OS Independent
Classifier: Topic :: Scientific/Engineering
Classifier: Topic :: Security
Requires-Python: >=3.9
Requires-Dist: importlib_resources; python_version < "3.9"
Requires-Dist: pyusb
Requires-Dist: future
Requires-Dist: pyfwup>=0.5.2
Requires-Dist: tqdm
Requires-Dist: setuptools
Requires-Dist: cmsis_svd
Requires-Dist: tabulate
Requires-Dist: prompt_toolkit
Requires-Dist: pygreat
Requires-Dist: ipython
